{
  "sections": {
    "main": {
      "type": "main-product",
      "blocks": {
        "vendor": {
          "type": "text",
          "settings": {
            "text": "",
            "text_style": "uppercase"
          }
        },
        "title": {
          "type": "title",
          "settings": {
          }
        },
        "subtitle": {
          "type": "text",
          "settings": {
            "text": "",
            "text_style": "subtitle"
          }
        },
        "price": {
          "type": "price",
          "settings": {
          }
        },
        "variant_picker": {
          "type": "variant_picker",
          "settings": {
            "picker_type": "button"
          }
        },
        "quantity_selector": {
          "type": "quantity_selector",
          "settings": {
          }
        },
        "buy_buttons": {
          "type": "buy_buttons",
          "settings": {
            "show_dynamic_checkout": false
          }
        },
        "description": {
          "type": "description",
          "settings": {
          }
        },
        "share": {
          "type": "share",
          "disabled": true,
          "settings": {
            "share_label": "Share"
          }
        },
        "82ed46af-ab0b-4456-a38c-709f3dad4140": {
          "type": "rating",
          "settings": {
          }
        },
        "dab4f463-533d-4cc5-b603-e1286bb763ed": {
          "type": "shopify:\/\/apps\/product-reviews\/blocks\/reviews\/bae150af-8da8-48b2-9867-398188115e5f",
          "settings": {
          }
        },
        "3b5d190a-c140-441d-a430-823462f6fa1c": {
          "type": "shopify:\/\/apps\/product-reviews\/blocks\/star_rating\/bae150af-8da8-48b2-9867-398188115e5f",
          "disabled": true,
          "settings": {
            "stars_fill_color": "#000000",
            "star_size": 15,
            "text_align": "center",
            "product": "{{product}}",
            "stars_text_empty": "No reviews"
          }
        }
      },
      "block_order": [
        "vendor",
        "title",
        "subtitle",
        "price",
        "variant_picker",
        "quantity_selector",
        "buy_buttons",
        "description",
        "share",
        "82ed46af-ab0b-4456-a38c-709f3dad4140",
        "dab4f463-533d-4cc5-b603-e1286bb763ed",
        "3b5d190a-c140-441d-a430-823462f6fa1c"
      ],
      "settings": {
        "enable_sticky_info": true,
        "hide_variants": false,
        "enable_video_looping": false
      }
    },
    "product-recommendations": {
      "type": "product-recommendations",
      "settings": {
        "heading": "You may also like",
        "image_ratio": "adapt",
        "show_secondary_image": false,
        "add_image_padding": false,
        "show_image_outline": true,
        "show_vendor": false,
        "show_rating": false
      }
    }
  },
  "order": [
    "main",
    "product-recommendations"
  ]
}
